LICENSE
MANIFEST.in
README.rst
setup.py
chembl_core_model/__init__.py
chembl_core_model/tests.py
chembl_core_model.egg-info/PKG-INFO
chembl_core_model.egg-info/SOURCES.txt
chembl_core_model.egg-info/dependency_links.txt
chembl_core_model.egg-info/not-zip-safe
chembl_core_model.egg-info/requires.txt
chembl_core_model.egg-info/top_level.txt
chembl_core_model/models/__init__.py
chembl_core_model/models/approvedDrugData.py
chembl_core_model/models/bindingSiteInformation.py
chembl_core_model/models/compounds.py
chembl_core_model/models/drugMetabolismData.py
chembl_core_model/models/experimentalData.py
chembl_core_model/models/general.py
chembl_core_model/models/mechanismAnnotation.py
chembl_core_model/models/sourceInformation.py
chembl_core_model/models/targetInformation.py