Metadata-Version: 1.1
Name: chembl-core-model
Version: 0.9.26
Summary: Core ChEMBL python ORM model
Home-page: https://www.ebi.ac.uk/chembl/
Author: Michal Nowotka
Author-email: mnowotka@ebi.ac.uk
License: Apache Software License
Platform: UNKNOWN
Classifier: Development Status :: 4 - Beta
Classifier: Environment :: Web Environment
Classifier: Framework :: Django
Classifier: Intended Audience :: Developers
Classifier: License :: OSI Approved :: Apache Software License
Classifier: Operating System :: POSIX :: Linux
Classifier: Programming Language :: Python :: 2.7
Classifier: Topic :: Scientific/Engineering :: Chemistry
